pprintast/__init__.py
pprintast/__main__.py
pprintast/pprintast.py
pprintast/test_pprintast.py
pprintast-1.2.1.dist-info/LICENSE
pprintast-1.2.1.dist-info/METADATA
pprintast-1.2.1.dist-info/WHEEL
pprintast-1.2.1.dist-info/entry_points.txt
pprintast-1.2.1.dist-info/top_level.txt
pprintast-1.2.1.dist-info/RECORD
