Metadata-Version: 2.1
Name: pprintast
Version: 1.2.1
Summary: A AST pretty printer for python.
Home-page: https://github.com/clarketm/pprintast
Author: Travis Clarke, Alex Leone
Author-email: travis.m.clarke@gmail.com, acleone@gmail.com
License: UNKNOWN
Platform: UNKNOWN
Classifier: Intended Audience :: Developers
Classifier: Natural Language :: English
Classifier: Programming Language :: Python :: 3
Classifier: Programming Language :: Python :: 3.6
Classifier: Programming Language :: Python :: 3.7
Classifier: License :: OSI Approved :: MIT License
Classifier: Operating System :: OS Independent
Classifier: Environment :: Console
Requires-Python: >=3.6
